{
    "type": "FeatureCollection",
    "features": [
        {
            "type": "Feature",
            "properties": {
                "route_ref:De_Lijn": "54",
                "ref:De_Lijn": "506329",
                "bus": "yes",
                "name": "Oostende Ostend Stores",
                "public_transport": "platform",
                "highway": "bus_stop",
                "created_by": "OUDENBURGSESTEENWEG OOSTENDE",
                "operator": "De Lijn",
                "network": "DLWV"
            },
            "geometry": {
                "type": "Point",
                "coordinates": [
                    2.957075,
                    51.220218
                ]
            }
        },
        {
            "type": "Feature",
            "properties": {
                "route_ref:De_Lijn": "21;22;23",
                "ref:De_Lijn": "506351",
                "bus": "yes",
                "name": "Oostende Vesuvius",
                "public_transport": "platform",
                "highway": "bus_stop",
                "created_by": "ZANDVOORDESTRAAT OOSTENDE",
                "operator": "De Lijn",
                "network": "DLWV"
            },
            "geometry": {
                "type": "Point",
                "coordinates": [
                    2.9589,
                    51.210521
                ]
            }
        },
        {
            "type": "Feature",
            "properties": {
                "route_ref:De_Lijn": "54",
                "ref:De_Lijn": "506588",
                "bus": "yes",
                "name": "Oostende Oesterbank",
                "public_transport": "platform",
                "highway": "bus_stop",
                "created_by": "VAARTBLEKERSSTRAAT OOSTENDE",
                "operator": "De Lijn",
                "network": "DLWV"
            },
            "geometry": {
                "type": "Point",
                "coordinates": [
                    2.950908,
                    51.220566
                ]
            }
        },
        {
            "type": "Feature",
            "properties": {
                "route_ref:De_Lijn": "21;22;23;82",
                "ref:De_Lijn": "501356",
                "bus": "yes",
                "name": "Oostende Waterzuiveringsstation",
                "public_transport": "platform",
                "highway": "bus_stop",
                "created_by": "ZANDVOORDESTRAAT OOSTENDE",
                "operator": "De Lijn",
                "network": "DLWV"
            },
            "geometry": {
                "type": "Point",
                "coordinates": [
                    2.952002,
                    51.211904
                ]
            }
        },
        {
            "type": "Feature",
            "properties": {
                "route_ref:De_Lijn": "21;22;23",
                "ref:De_Lijn": "506308",
                "bus": "yes",
                "name": "Oostende Koebrugstraat",
                "public_transport": "platform",
                "highway": "bus_stop",
                "created_by": "ZANDVOORDESTRAAT OOSTENDE",
                "operator": "De Lijn",
                "network": "DLWV"
            },
            "geometry": {
                "type": "Point",
                "coordinates": [
                    2.944592,
                    51.21364
                ]
            }
        },
        {
            "type": "Feature",
            "properties": {
                "route_ref:De_Lijn": "21;22;23;82",
                "ref:De_Lijn": "501308",
                "bus": "yes",
                "name": "Oostende Koebrugstraat",
                "public_transport": "platform",
                "highway": "bus_stop",
                "created_by": "ZANDVOORDESTRAAT OOSTENDE",
                "operator": "De Lijn",
                "network": "DLWV"
            },
            "geometry": {
                "type": "Point",
                "coordinates": [
                    2.945143,
                    51.213404
                ]
            }
        },
        {
            "type": "Feature",
            "properties": {
                "route_ref:De_Lijn": "21;22;23",
                "ref:De_Lijn": "506356",
                "bus": "yes",
                "name": "Oostende Waterzuiveringsstation",
                "public_transport": "platform",
                "highway": "bus_stop",
                "created_by": "ZANDVOORDESTRAAT OOSTENDE",
                "operator": "De Lijn",
                "network": "DLWV"
            },
            "geometry": {
                "type": "Point",
                "coordinates": [
                    2.951595,
                    51.212115
                ]
            }
        },
        {
            "type": "Feature",
            "properties": {
                "route_ref:De_Lijn": "21;22;23;82",
                "ref:De_Lijn": "501351",
                "bus": "yes",
                "name": "Oostende Vesuvius",
                "public_transport": "platform",
                "highway": "bus_stop",
                "created_by": "ZANDVOORDESTRAAT OOSTENDE",
                "operator": "De Lijn",
                "network": "DLWV"
            },
            "geometry": {
                "type": "Point",
                "coordinates": [
                    2.959681,
                    51.210234
                ]
            }
        },
        {
            "type": "Feature",
            "properties": {
                "route_ref:De_Lijn": "54",
                "ref:De_Lijn": "501329",
                "bus": "yes",
                "name": "Oostende Ostend Stores",
                "public_transport": "platform",
                "highway": "bus_stop",
                "created_by": "OUDENBURGSESTEENWEG OOSTENDE",
                "operator": "De Lijn",
                "network": "DLWV"
            },
            "geometry": {
                "type": "Point",
                "coordinates": [
                    2.957223,
                    51.220066
                ]
            }
        },
        {
            "type": "Feature",
            "properties": {
                "route_ref:De_Lijn": "54",
                "ref:De_Lijn": "501588",
                "bus": "yes",
                "name": "Oostende Oesterbank",
                "public_transport": "platform",
                "highway": "bus_stop",
                "created_by": "VAARTBLEKERSSTRAAT OOSTENDE",
                "operator": "De Lijn",
                "network": "DLWV"
            },
            "geometry": {
                "type": "Point",
                "coordinates": [
                    2.950955,
                    51.22045
                ]
            }
        }
    ]
}