{
    "type": "FeatureCollection",
    "features": [
        {
            "type": "Feature",
            "properties": {
                "route_ref:De_Lijn": "71",
                "ref:De_Lijn": "208581",
                "bus": "yes",
                "name": "Tollembeek Hollestraat",
                "public_transport": "platform",
                "highway": "bus_stop",
                "created_by": "HOLLESTRAAT TOLLEMBEEK",
                "operator": "De Lijn",
                "network": "DLOV"
            },
            "geometry": {
                "type": "Point",
                "coordinates": [
                    4.011755,
                    50.745082
                ]
            }
        },
        {
            "type": "Feature",
            "properties": {
                "ref:De_Lijn": "209580",
                "bus": "yes",
                "name": "Tollembeek Smedries",
                "public_transport": "platform",
                "odbl": "new",
                "highway": "bus_stop",
                "created_by": "HOLLESTRAAT TOLLEMBEEK",
                "operator": "De Lijn",
                "network": "DLOV"
            },
            "geometry": {
                "type": "Point",
                "coordinates": [
                    4.005247,
                    50.74926
                ]
            }
        },
        {
            "type": "Feature",
            "properties": {
                "route_ref:De_Lijn": "102;161",
                "ref:De_Lijn": "307298",
                "bus": "yes",
                "name": "Tollembeek Oude School",
                "public_transport": "platform",
                "highway": "bus_stop",
                "created_by": "PLAATSSTRAAT TOLLEMBEEK",
                "operator": "De Lijn",
                "network": "DLVB"
            },
            "geometry": {
                "type": "Point",
                "coordinates": [
                    4.002679,
                    50.742438
                ]
            }
        },
        {
            "type": "Feature",
            "properties": {
                "route_ref:De_Lijn": "102;161;732",
                "ref:De_Lijn": "301424",
                "bus": "yes",
                "name": "Tollembeek Hollestraat",
                "public_transport": "platform",
                "highway": "bus_stop",
                "created_by": "VOLLEZELESTRAAT TOLLEMBEEK",
                "operator": "De Lijn",
                "network": "DLVB"
            },
            "geometry": {
                "type": "Point",
                "coordinates": [
                    4.012589,
                    50.745318
                ]
            }
        },
        {
            "type": "Feature",
            "properties": {
                "route_ref:De_Lijn": "71;161;732",
                "ref:De_Lijn": "305446",
                "bus": "yes",
                "name": "Tollembeek Plaats",
                "public_transport": "platform",
                "highway": "bus_stop",
                "created_by": "PLAATS TOLLEMBEEK",
                "operator": "De Lijn",
                "network": "DLVB"
            },
            "geometry": {
                "type": "Point",
                "coordinates": [
                    4.006852,
                    50.741363
                ]
            }
        },
        {
            "type": "Feature",
            "properties": {
                "route_ref:De_Lijn": "71;102",
                "ref:De_Lijn": "306268",
                "bus": "yes",
                "name": "Tollembeek Hernestraat",
                "public_transport": "platform",
                "highway": "bus_stop",
                "created_by": "HERNESTRAAT TOLLEMBEEK",
                "operator": "De Lijn",
                "network": "DLVB"
            },
            "geometry": {
                "type": "Point",
                "coordinates": [
                    4.015692,
                    50.737713
                ]
            }
        },
        {
            "type": "Feature",
            "properties": {
                "route_ref:De_Lijn": "71;161",
                "ref:De_Lijn": "305447",
                "bus": "yes",
                "name": "Tollembeek Plaats",
                "public_transport": "platform",
                "highway": "bus_stop",
                "created_by": "PLAATS TOLLEMBEEK",
                "operator": "De Lijn",
                "network": "DLVB"
            },
            "geometry": {
                "type": "Point",
                "coordinates": [
                    4.007093,
                    50.741373
                ]
            }
        },
        {
            "type": "Feature",
            "properties": {
                "route_ref:De_Lijn": "102;161;732",
                "ref:De_Lijn": "307299",
                "bus": "yes",
                "name": "Tollembeek Oude School",
                "public_transport": "platform",
                "highway": "bus_stop",
                "created_by": "PLAATSSTRAAT TOLLEMBEEK",
                "operator": "De Lijn",
                "network": "DLVB"
            },
            "geometry": {
                "type": "Point",
                "coordinates": [
                    4.001698,
                    50.742884
                ]
            }
        },
        {
            "type": "Feature",
            "properties": {
                "route_ref:De_Lijn": "71;102",
                "ref:De_Lijn": "307326",
                "bus": "yes",
                "name": "Tollembeek Schoolstraat",
                "public_transport": "platform",
                "highway": "bus_stop",
                "created_by": "HERNESTRAAT TOLLEMBEEK",
                "operator": "De Lijn",
                "network": "DLVB"
            },
            "geometry": {
                "type": "Point",
                "coordinates": [
                    4.008883,
                    50.740695
                ]
            }
        },
        {
            "type": "Feature",
            "properties": {
                "route_ref:De_Lijn": "71;102",
                "ref:De_Lijn": "306267",
                "bus": "yes",
                "name": "Tollembeek Hernestraat",
                "public_transport": "platform",
                "highway": "bus_stop",
                "created_by": "HERNESTRAAT TOLLEMBEEK",
                "operator": "De Lijn",
                "network": "DLVB"
            },
            "geometry": {
                "type": "Point",
                "coordinates": [
                    4.015726,
                    50.73881
                ]
            }
        },
        {
            "type": "Feature",
            "properties": {
                "route_ref:De_Lijn": "71;102",
                "ref:De_Lijn": "307322",
                "bus": "yes",
                "name": "Tollembeek Smedries",
                "public_transport": "platform",
                "highway": "bus_stop",
                "created_by": "HOLLESTRAAT TOLLEMBEEK",
                "operator": "De Lijn",
                "network": "DLVB"
            },
            "geometry": {
                "type": "Point",
                "coordinates": [
                    4.005233,
                    50.749269
                ]
            }
        },
        {
            "type": "Feature",
            "properties": {
                "ref:De_Lijn": "208580",
                "bus": "yes",
                "name": "Tollembeek Smedries",
                "public_transport": "platform",
                "odbl": "new",
                "highway": "bus_stop",
                "created_by": "HOLLESTRAAT TOLLEMBEEK",
                "operator": "De Lijn",
                "network": "DLOV"
            },
            "geometry": {
                "type": "Point",
                "coordinates": [
                    4.004822,
                    50.749268
                ]
            }
        },
        {
            "type": "Feature",
            "properties": {
                "route_ref:De_Lijn": "71;102",
                "ref:De_Lijn": "307323",
                "bus": "yes",
                "name": "Tollembeek Smedries",
                "public_transport": "platform",
                "highway": "bus_stop",
                "created_by": "HOLLESTRAAT TOLLEMBEEK",
                "operator": "De Lijn",
                "network": "DLVB"
            },
            "geometry": {
                "type": "Point",
                "coordinates": [
                    4.00478,
                    50.749277
                ]
            }
        },
        {
            "type": "Feature",
            "properties": {
                "route_ref:De_Lijn": "102;161",
                "ref:De_Lijn": "307296",
                "bus": "yes",
                "name": "Tollembeek Statiestraat",
                "public_transport": "platform",
                "highway": "bus_stop",
                "created_by": "PLAATSSTRAAT TOLLEMBEEK",
                "operator": "De Lijn",
                "network": "DLVB"
            },
            "geometry": {
                "type": "Point",
                "coordinates": [
                    4.005406,
                    50.741557
                ]
            }
        },
        {
            "type": "Feature",
            "properties": {
                "route_ref:De_Lijn": "102;161;732",
                "ref:De_Lijn": "307297",
                "bus": "yes",
                "name": "Tollembeek Statiestraat",
                "public_transport": "platform",
                "highway": "bus_stop",
                "created_by": "PLAATSSTRAAT TOLLEMBEEK",
                "operator": "De Lijn",
                "network": "DLVB"
            },
            "geometry": {
                "type": "Point",
                "coordinates": [
                    4.005689,
                    50.741611
                ]
            }
        },
        {
            "type": "Feature",
            "properties": {
                "route_ref:De_Lijn": "71;102",
                "ref:De_Lijn": "307327",
                "bus": "yes",
                "name": "Tollembeek Schoolstraat",
                "public_transport": "platform",
                "highway": "bus_stop",
                "created_by": "HERNESTRAAT TOLLEMBEEK",
                "operator": "De Lijn",
                "network": "DLVB"
            },
            "geometry": {
                "type": "Point",
                "coordinates": [
                    4.008828,
                    50.740596
                ]
            }
        },
        {
            "type": "Feature",
            "properties": {
                "ref:De_Lijn": "306266",
                "bus": "yes",
                "name": "Tollembeek Marktplein",
                "public_transport": "platform",
                "highway": "bus_stop",
                "created_by": "PLAATS TOLLEMBEEK",
                "operator": "De Lijn",
                "network": "DLVB"
            },
            "geometry": {
                "type": "Point",
                "coordinates": [
                    4.006852,
                    50.741363
                ]
            }
        },
        {
            "type": "Feature",
            "properties": {
                "route_ref:De_Lijn": "71;102;161",
                "ref:De_Lijn": "301423",
                "bus": "yes",
                "name": "Tollembeek Hollestraat",
                "public_transport": "platform",
                "highway": "bus_stop",
                "created_by": "VOLLEZELESTRAAT TOLLEMBEEK",
                "operator": "De Lijn",
                "network": "DLVB"
            },
            "geometry": {
                "type": "Point",
                "coordinates": [
                    4.012266,
                    50.744922
                ]
            }
        },
        {
            "type": "Feature",
            "properties": {
                "ref:De_Lijn": "306265",
                "bus": "yes",
                "name": "Tollembeek Marktplein",
                "public_transport": "platform",
                "highway": "bus_stop",
                "created_by": "PLAATS TOLLEMBEEK",
                "operator": "De Lijn",
                "network": "DLVB"
            },
            "geometry": {
                "type": "Point",
                "coordinates": [
                    4.007093,
                    50.741373
                ]
            }
        }
    ]
}