{
    "type": "FeatureCollection",
    "features": [
        {
            "type": "Feature",
            "properties": {
                "route_ref:De_Lijn": "242;245;543",
                "ref:De_Lijn": "303823",
                "bus": "yes",
                "name": "Brussegem Noorden",
                "public_transport": "platform",
                "highway": "bus_stop",
                "created_by": "BRUSSELSESTEENWEG BRUSSEGEM",
                "operator": "De Lijn",
                "network": "DLVB"
            },
            "geometry": {
                "type": "Point",
                "coordinates": [
                    4.26441,
                    50.926421
                ]
            }
        },
        {
            "type": "Feature",
            "properties": {
                "route_ref:De_Lijn": "242;245;543",
                "ref:De_Lijn": "303822",
                "bus": "yes",
                "name": "Brussegem Noorden",
                "public_transport": "platform",
                "highway": "bus_stop",
                "created_by": "BRUSSELSESTEENWEG BRUSSEGEM",
                "operator": "De Lijn",
                "network": "DLVB"
            },
            "geometry": {
                "type": "Point",
                "coordinates": [
                    4.264552,
                    50.926511
                ]
            }
        },
        {
            "type": "Feature",
            "properties": {
                "route_ref:De_Lijn": "242;245;543",
                "ref:De_Lijn": "303826",
                "bus": "yes",
                "name": "Hamme Guduladreef",
                "public_transport": "platform",
                "highway": "bus_stop",
                "created_by": "BRUSSELSESTEENWEG HAMME (MERCHTEM)",
                "operator": "De Lijn",
                "network": "DLVB"
            },
            "geometry": {
                "type": "Point",
                "coordinates": [
                    4.283324,
                    50.92018
                ]
            }
        },
        {
            "type": "Feature",
            "properties": {
                "route_ref:De_Lijn": "242;245;543",
                "ref:De_Lijn": "303818",
                "bus": "yes",
                "name": "Brussegem Kerkhof",
                "public_transport": "platform",
                "highway": "bus_stop",
                "created_by": "BRUSSELSESTEENWEG BRUSSEGEM",
                "operator": "De Lijn",
                "network": "DLVB"
            },
            "geometry": {
                "type": "Point",
                "coordinates": [
                    4.270245,
                    50.924925
                ]
            }
        },
        {
            "type": "Feature",
            "properties": {
                "route_ref:De_Lijn": "242;245;543",
                "ref:De_Lijn": "303825",
                "bus": "yes",
                "name": "Brussegem Ossel Dorp",
                "public_transport": "platform",
                "highway": "bus_stop",
                "created_by": "BRUSSELSESTEENWEG HAMME (MERCHTEM)",
                "operator": "De Lijn",
                "network": "DLVB"
            },
            "geometry": {
                "type": "Point",
                "coordinates": [
                    4.278926,
                    50.92219
                ]
            }
        },
        {
            "type": "Feature",
            "properties": {
                "route_ref:De_Lijn": "242;245;543",
                "ref:De_Lijn": "303819",
                "bus": "yes",
                "name": "Brussegem Kerkhof",
                "public_transport": "platform",
                "highway": "bus_stop",
                "created_by": "BRUSSELSESTEENWEG BRUSSEGEM",
                "operator": "De Lijn",
                "network": "DLVB"
            },
            "geometry": {
                "type": "Point",
                "coordinates": [
                    4.27033,
                    50.924772
                ]
            }
        },
        {
            "type": "Feature",
            "properties": {
                "route_ref:De_Lijn": "242;245;543",
                "ref:De_Lijn": "303827",
                "bus": "yes",
                "name": "Hamme Guduladreef",
                "public_transport": "platform",
                "highway": "bus_stop",
                "created_by": "BRUSSELSESTEENWEG HAMME (MERCHTEM)",
                "operator": "De Lijn",
                "network": "DLVB"
            },
            "geometry": {
                "type": "Point",
                "coordinates": [
                    4.28277,
                    50.920224
                ]
            }
        },
        {
            "type": "Feature",
            "properties": {
                "ref:De_Lijn": "308581",
                "bus": "yes",
                "name": "Brussegem Torenhof",
                "public_transport": "platform",
                "highway": "bus_stop",
                "created_by": "NIEUWELAAN BRUSSEGEM",
                "operator": "De Lijn",
                "network": "DLVB"
            },
            "geometry": {
                "type": "Point",
                "coordinates": [
                    4.266879,
                    50.929255
                ]
            }
        },
        {
            "type": "Feature",
            "properties": {
                "route_ref:De_Lijn": "242;245;543",
                "ref:De_Lijn": "303824",
                "bus": "yes",
                "name": "Brussegem Ossel Dorp",
                "public_transport": "platform",
                "highway": "bus_stop",
                "created_by": "BRUSSELSESTEENWEG HAMME (MERCHTEM)",
                "operator": "De Lijn",
                "network": "DLVB"
            },
            "geometry": {
                "type": "Point",
                "coordinates": [
                    4.279168,
                    50.922226
                ]
            }
        }
    ]
}