{
    "type": "FeatureCollection",
    "features": [
        {
            "type": "Feature",
            "properties": {
                "route_ref:De_Lijn": "130;131;132;135",
                "ref:De_Lijn": "106905",
                "bus": "yes",
                "name": "Lint Reynaertshof",
                "public_transport": "platform",
                "highway": "bus_stop",
                "created_by": "KONTICHSESTEENWEG LINT",
                "operator": "De Lijn",
                "network": "DLAn"
            },
            "geometry": {
                "type": "Point",
                "coordinates": [
                    4.480096,
                    51.129529
                ]
            }
        },
        {
            "type": "Feature",
            "properties": {
                "route_ref:De_Lijn": "92;130;135",
                "ref:De_Lijn": "106901",
                "bus": "yes",
                "name": "Kontich Station Perron 1",
                "public_transport": "platform",
                "highway": "bus_stop",
                "created_by": "GANZENBOLLAAN KONTICH",
                "operator": "De Lijn",
                "network": "DLAn"
            },
            "geometry": {
                "type": "Point",
                "coordinates": [
                    4.475936,
                    51.134243
                ]
            }
        },
        {
            "type": "Feature",
            "properties": {
                "route_ref:De_Lijn": "92;130;131;132;135",
                "ref:De_Lijn": "104027",
                "bus": "yes",
                "name": "Kontich Elshagenlaan",
                "public_transport": "platform",
                "highway": "bus_stop",
                "created_by": "KAUWLEI KONTICH",
                "operator": "De Lijn",
                "network": "DLAn"
            },
            "geometry": {
                "type": "Point",
                "coordinates": [
                    4.47226,
                    51.132602
                ]
            }
        },
        {
            "type": "Feature",
            "properties": {
                "ref:De_Lijn": "100284",
                "bus": "yes",
                "name": "Kontich Weg op Lint NB2000",
                "public_transport": "platform",
                "odbl": "new",
                "highway": "bus_stop",
                "created_by": "KAUWLEI KONTICH",
                "operator": "De Lijn",
                "network": "DLAn"
            },
            "geometry": {
                "type": "Point",
                "coordinates": [
                    4.469822,
                    51.134995
                ]
            }
        },
        {
            "type": "Feature",
            "properties": {
                "route_ref:De_Lijn": "130;132;135",
                "ref:De_Lijn": "106902",
                "bus": "yes",
                "name": "Kontich Station Perron 2",
                "public_transport": "platform",
                "highway": "bus_stop",
                "created_by": "GANZENBOLLAAN KONTICH",
                "operator": "De Lijn",
                "network": "DLAn"
            },
            "geometry": {
                "type": "Point",
                "coordinates": [
                    4.476035,
                    51.134073
                ]
            }
        },
        {
            "type": "Feature",
            "properties": {
                "route_ref:De_Lijn": "92;130;131;132;135",
                "ref:De_Lijn": "106900",
                "bus": "yes",
                "name": "Kontich Weg op Lint",
                "public_transport": "platform",
                "highway": "bus_stop",
                "created_by": "OOSTSTATIESTRAAT KONTICH",
                "operator": "De Lijn",
                "network": "DLAn"
            },
            "geometry": {
                "type": "Point",
                "coordinates": [
                    4.470451,
                    51.135066
                ]
            }
        },
        {
            "type": "Feature",
            "properties": {
                "route_ref:De_Lijn": "92;130;132;135",
                "ref:De_Lijn": "104026",
                "bus": "yes",
                "name": "Kontich Elshagenlaan",
                "public_transport": "platform",
                "highway": "bus_stop",
                "created_by": "KAUWLEI KONTICH",
                "operator": "De Lijn",
                "network": "DLAn"
            },
            "geometry": {
                "type": "Point",
                "coordinates": [
                    4.472346,
                    51.13271
                ]
            }
        },
        {
            "type": "Feature",
            "properties": {
                "route_ref:De_Lijn": "130;131;132;135",
                "ref:De_Lijn": "103043",
                "bus": "yes",
                "name": "Kontich Station Perron 3",
                "public_transport": "platform",
                "highway": "bus_stop",
                "created_by": "GANZENBOLLAAN KONTICH",
                "operator": "De Lijn",
                "network": "DLAn"
            },
            "geometry": {
                "type": "Point",
                "coordinates": [
                    4.476106,
                    51.133947
                ]
            }
        },
        {
            "type": "Feature",
            "properties": {
                "route_ref:De_Lijn": "92",
                "ref:De_Lijn": "104017",
                "bus": "yes",
                "name": "Kontich Vekenveld",
                "public_transport": "platform",
                "highway": "bus_stop",
                "created_by": "HOLLE WEG KONTICH",
                "operator": "De Lijn",
                "network": "DLAn"
            },
            "geometry": {
                "type": "Point",
                "coordinates": [
                    4.472618,
                    51.126516
                ]
            }
        },
        {
            "type": "Feature",
            "properties": {
                "route_ref:De_Lijn": "92",
                "ref:De_Lijn": "104016",
                "bus": "yes",
                "name": "Kontich Vekenveld",
                "public_transport": "platform",
                "highway": "bus_stop",
                "created_by": "HOLLE WEG KONTICH",
                "operator": "De Lijn",
                "network": "DLAn"
            },
            "geometry": {
                "type": "Point",
                "coordinates": [
                    4.472789,
                    51.126525
                ]
            }
        },
        {
            "type": "Feature",
            "properties": {
                "route_ref:De_Lijn": "92;130;131;132;135",
                "ref:De_Lijn": "106899",
                "bus": "yes",
                "name": "Kontich Weg op Lint",
                "public_transport": "platform",
                "highway": "bus_stop",
                "created_by": "OOSTSTATIESTRAAT KONTICH",
                "operator": "De Lijn",
                "network": "DLAn"
            },
            "geometry": {
                "type": "Point",
                "coordinates": [
                    4.470894,
                    51.13485
                ]
            }
        },
        {
            "type": "Feature",
            "properties": {
                "ref:De_Lijn": "100285",
                "bus": "yes",
                "name": "Kontich Weg op Lint NB2000",
                "public_transport": "platform",
                "odbl": "new",
                "highway": "bus_stop",
                "created_by": "KAUWLEI KONTICH",
                "operator": "De Lijn",
                "network": "DLAn"
            },
            "geometry": {
                "type": "Point",
                "coordinates": [
                    4.469994,
                    51.135049
                ]
            }
        },
        {
            "type": "Feature",
            "properties": {
                "route_ref:De_Lijn": "130;131;132;135",
                "ref:De_Lijn": "104025",
                "bus": "yes",
                "name": "Kontich Hof Van Spruytlaan",
                "public_transport": "platform",
                "highway": "bus_stop",
                "created_by": "OOSTSTATIESTRAAT KONTICH",
                "operator": "De Lijn",
                "network": "DLAn"
            },
            "geometry": {
                "type": "Point",
                "coordinates": [
                    4.461208,
                    51.1352
                ]
            }
        },
        {
            "type": "Feature",
            "properties": {
                "route_ref:De_Lijn": "130;132;135",
                "ref:De_Lijn": "106906",
                "bus": "yes",
                "name": "Lint Reynaertshof",
                "public_transport": "platform",
                "highway": "bus_stop",
                "created_by": "KONTICHSESTEENWEG LINT",
                "operator": "De Lijn",
                "network": "DLAn"
            },
            "geometry": {
                "type": "Point",
                "coordinates": [
                    4.480467,
                    51.129403
                ]
            }
        },
        {
            "type": "Feature",
            "properties": {
                "route_ref:De_Lijn": "92;130;131;132;135",
                "ref:De_Lijn": "104013",
                "bus": "yes",
                "name": "Kontich Hoge Akker",
                "public_transport": "platform",
                "highway": "bus_stop",
                "created_by": "KAUWLEI KONTICH",
                "operator": "De Lijn",
                "network": "DLAn"
            },
            "geometry": {
                "type": "Point",
                "coordinates": [
                    4.474439,
                    51.129463
                ]
            }
        },
        {
            "type": "Feature",
            "properties": {
                "route_ref:De_Lijn": "130;132;135",
                "ref:De_Lijn": "104024",
                "bus": "yes",
                "name": "Kontich Hof Van Spruytlaan",
                "public_transport": "platform",
                "highway": "bus_stop",
                "created_by": "OOSTSTATIESTRAAT KONTICH",
                "operator": "De Lijn",
                "network": "DLAn"
            },
            "geometry": {
                "type": "Point",
                "coordinates": [
                    4.461179,
                    51.135308
                ]
            }
        },
        {
            "type": "Feature",
            "properties": {
                "route_ref:De_Lijn": "92;130;132;135",
                "ref:De_Lijn": "104014",
                "bus": "yes",
                "name": "Kontich Hoge Akker",
                "public_transport": "platform",
                "highway": "bus_stop",
                "created_by": "KAUWLEI KONTICH",
                "operator": "De Lijn",
                "network": "DLAn"
            },
            "geometry": {
                "type": "Point",
                "coordinates": [
                    4.474582,
                    51.129544
                ]
            }
        }
    ]
}