{
    "type": "FeatureCollection",
    "features": [
        {
            "type": "Feature",
            "properties": {
                "route_ref:De_Lijn": "15c",
                "ref:De_Lijn": "400348",
                "bus": "yes",
                "name": "Balen Scheps",
                "public_transport": "platform",
                "highway": "bus_stop",
                "created_by": "SCHEPS BALEN",
                "operator": "De Lijn",
                "network": "DLLi"
            },
            "geometry": {
                "type": "Point",
                "coordinates": [
                    5.171487,
                    51.156692
                ]
            }
        },
        {
            "type": "Feature",
            "properties": {
                "route_ref:De_Lijn": "15c;732",
                "ref:De_Lijn": "400353",
                "bus": "yes",
                "name": "Schoor Intermarché",
                "public_transport": "platform",
                "highway": "bus_stop",
                "created_by": "SCHOOR BALEN",
                "operator": "De Lijn",
                "network": "DLLi"
            },
            "geometry": {
                "type": "Point",
                "coordinates": [
                    5.179434,
                    51.164907
                ]
            }
        },
        {
            "type": "Feature",
            "properties": {
                "route_ref:De_Lijn": "733",
                "ref:De_Lijn": "400427",
                "bus": "yes",
                "name": "Balen Hoolstmolenstraat",
                "public_transport": "platform",
                "highway": "bus_stop",
                "created_by": "HOOLSTERBERG BALEN",
                "operator": "De Lijn",
                "network": "DLLi"
            },
            "geometry": {
                "type": "Point",
                "coordinates": [
                    5.164334,
                    51.157207
                ]
            }
        },
        {
            "type": "Feature",
            "properties": {
                "route_ref:De_Lijn": "15c;732",
                "ref:De_Lijn": "400360",
                "bus": "yes",
                "name": "Balen Schoor",
                "public_transport": "platform",
                "highway": "bus_stop",
                "created_by": "SCHOOR BALEN",
                "operator": "De Lijn",
                "network": "DLLi"
            },
            "geometry": {
                "type": "Point",
                "coordinates": [
                    5.183623,
                    51.163251
                ]
            }
        },
        {
            "type": "Feature",
            "properties": {
                "route_ref:De_Lijn": "15c;732",
                "ref:De_Lijn": "400352",
                "bus": "yes",
                "name": "Schoor Intermarché",
                "public_transport": "platform",
                "highway": "bus_stop",
                "created_by": "SCHOOR BALEN",
                "operator": "De Lijn",
                "network": "DLLi"
            },
            "geometry": {
                "type": "Point",
                "coordinates": [
                    5.179181,
                    51.165161
                ]
            }
        },
        {
            "type": "Feature",
            "properties": {
                "route_ref:De_Lijn": "15c;170;732;733",
                "ref:De_Lijn": "102492",
                "bus": "yes",
                "name": "Balen Hoolsterberg",
                "public_transport": "platform",
                "highway": "bus_stop",
                "created_by": "HOOLSTERBERG BALEN",
                "operator": "De Lijn",
                "network": "DLAn"
            },
            "geometry": {
                "type": "Point",
                "coordinates": [
                    5.165859,
                    51.160289
                ]
            }
        },
        {
            "type": "Feature",
            "properties": {
                "ref:De_Lijn": "400340",
                "bus": "yes",
                "name": "Balen Reit",
                "public_transport": "platform",
                "odbl": "new",
                "highway": "bus_stop",
                "created_by": "REIT BALEN",
                "operator": "De Lijn",
                "network": "DLLi"
            },
            "geometry": {
                "type": "Point",
                "coordinates": [
                    5.166524,
                    51.164078
                ]
            }
        },
        {
            "type": "Feature",
            "properties": {
                "route_ref:De_Lijn": "15c",
                "ref:De_Lijn": "400396",
                "bus": "yes",
                "name": "Balen Windmolenstraat",
                "public_transport": "platform",
                "highway": "bus_stop",
                "created_by": "SCHEPS BALEN",
                "operator": "De Lijn",
                "network": "DLLi"
            },
            "geometry": {
                "type": "Point",
                "coordinates": [
                    5.182271,
                    51.159521
                ]
            }
        },
        {
            "type": "Feature",
            "properties": {
                "route_ref:De_Lijn": "15c",
                "ref:De_Lijn": "400382",
                "bus": "yes",
                "name": "Balen Vloedstraat",
                "public_transport": "platform",
                "highway": "bus_stop",
                "created_by": "SCHEPS BALEN",
                "operator": "De Lijn",
                "network": "DLLi"
            },
            "geometry": {
                "type": "Point",
                "coordinates": [
                    5.167261,
                    51.157008
                ]
            }
        },
        {
            "type": "Feature",
            "properties": {
                "route_ref:De_Lijn": "15c;170;732;733",
                "ref:De_Lijn": "102489",
                "bus": "yes",
                "name": "Balen Hoolsterberg",
                "public_transport": "platform",
                "highway": "bus_stop",
                "created_by": "HOOLSTERBERG BALEN",
                "operator": "De Lijn",
                "network": "DLAn"
            },
            "geometry": {
                "type": "Point",
                "coordinates": [
                    5.165896,
                    51.159939
                ]
            }
        },
        {
            "type": "Feature",
            "properties": {
                "ref:De_Lijn": "400341",
                "bus": "yes",
                "name": "Balen Reit",
                "public_transport": "platform",
                "odbl": "new",
                "highway": "bus_stop",
                "created_by": "REIT BALEN",
                "operator": "De Lijn",
                "network": "DLLi"
            },
            "geometry": {
                "type": "Point",
                "coordinates": [
                    5.16667,
                    51.164266
                ]
            }
        },
        {
            "type": "Feature",
            "properties": {
                "ref:De_Lijn": "400281",
                "bus": "yes",
                "name": "Balen Hoolsterberg",
                "public_transport": "platform",
                "odbl": "new",
                "highway": "bus_stop",
                "created_by": "HOOLSTERBERG BALEN",
                "operator": "De Lijn",
                "network": "DLLi"
            },
            "geometry": {
                "type": "Point",
                "coordinates": [
                    5.165826,
                    51.160029
                ]
            }
        },
        {
            "type": "Feature",
            "properties": {
                "route_ref:De_Lijn": "15c;733",
                "ref:De_Lijn": "400350",
                "bus": "yes",
                "name": "Balen Schepsveld",
                "public_transport": "platform",
                "highway": "bus_stop",
                "created_by": "SCHEPS BALEN",
                "operator": "De Lijn",
                "network": "DLLi"
            },
            "geometry": {
                "type": "Point",
                "coordinates": [
                    5.17598,
                    51.156967
                ]
            }
        },
        {
            "type": "Feature",
            "properties": {
                "route_ref:De_Lijn": "15c",
                "ref:De_Lijn": "400349",
                "bus": "yes",
                "name": "Balen Scheps",
                "public_transport": "platform",
                "highway": "bus_stop",
                "created_by": "SCHEPS BALEN",
                "operator": "De Lijn",
                "network": "DLLi"
            },
            "geometry": {
                "type": "Point",
                "coordinates": [
                    5.170942,
                    51.156596
                ]
            }
        },
        {
            "type": "Feature",
            "properties": {
                "ref:De_Lijn": "400280",
                "bus": "yes",
                "name": "Balen Hoolsterberg",
                "public_transport": "platform",
                "odbl": "new",
                "highway": "bus_stop",
                "created_by": "HOOLSTERBERG BALEN",
                "operator": "De Lijn",
                "network": "DLLi"
            },
            "geometry": {
                "type": "Point",
                "coordinates": [
                    5.165967,
                    51.15992
                ]
            }
        },
        {
            "type": "Feature",
            "properties": {
                "route_ref:De_Lijn": "15c",
                "ref:De_Lijn": "400383",
                "bus": "yes",
                "name": "Balen Vloedstraat",
                "public_transport": "platform",
                "highway": "bus_stop",
                "created_by": "SCHEPS BALEN",
                "operator": "De Lijn",
                "network": "DLLi"
            },
            "geometry": {
                "type": "Point",
                "coordinates": [
                    5.166878,
                    51.157217
                ]
            }
        },
        {
            "type": "Feature",
            "properties": {
                "route_ref:De_Lijn": "15c;732",
                "ref:De_Lijn": "400361",
                "bus": "yes",
                "name": "Balen Schoor",
                "public_transport": "platform",
                "highway": "bus_stop",
                "created_by": "SCHOOR BALEN",
                "operator": "De Lijn",
                "network": "DLLi"
            },
            "geometry": {
                "type": "Point",
                "coordinates": [
                    5.183592,
                    51.163117
                ]
            }
        },
        {
            "type": "Feature",
            "properties": {
                "route_ref:De_Lijn": "15c;733",
                "ref:De_Lijn": "400351",
                "bus": "yes",
                "name": "Balen Schepsveld",
                "public_transport": "platform",
                "highway": "bus_stop",
                "created_by": "SCHEPS BALEN",
                "operator": "De Lijn",
                "network": "DLLi"
            },
            "geometry": {
                "type": "Point",
                "coordinates": [
                    5.176209,
                    51.156974
                ]
            }
        },
        {
            "type": "Feature",
            "properties": {
                "route_ref:De_Lijn": "15c",
                "ref:De_Lijn": "400397",
                "bus": "yes",
                "name": "Balen Windmolenstraat",
                "public_transport": "platform",
                "highway": "bus_stop",
                "created_by": "SCHEPS BALEN",
                "operator": "De Lijn",
                "network": "DLLi"
            },
            "geometry": {
                "type": "Point",
                "coordinates": [
                    5.182532,
                    51.159717
                ]
            }
        }
    ]
}